BraineryBytes/BraineryBytes.pyd
BraineryBytes/__init__.py
BraineryBytes-0.0.8.dist-info/METADATA
BraineryBytes-0.0.8.dist-info/WHEEL
BraineryBytes-0.0.8.dist-info/top_level.txt
BraineryBytes-0.0.8.dist-info/RECORD
