Metadata-Version: 2.1
Name: BraineryBytes
Version: 0.0.8
Summary: A Series of function for Python
Author: Silvia Mazzoni
Author-email: <silviamazzoni@yahoo.com>
License: UNKNOWN
Keywords: python
Platform: UNKNOWN
Classifier: Development Status :: 1 - Planning
Classifier: Intended Audience :: Developers
Classifier: Programming Language :: Python :: 3
Classifier: Operating System :: Microsoft :: Windows
Requires-Dist: matplotlib
Requires-Dist: numpy
Requires-Dist: pandas
Requires-Dist: requests
